KafkaZhongwenWendang0100/README.md
KafkaZhongwenWendang0100/__init__.py
KafkaZhongwenWendang0100/__main__.py
KafkaZhongwenWendang0100/file.epub
KafkaZhongwenWendang0100/index.html
KafkaZhongwenWendang0100/css/__init__.py
KafkaZhongwenWendang0100/css/annotations.css
KafkaZhongwenWendang0100/css/main.css
KafkaZhongwenWendang0100/css/normalize.css
KafkaZhongwenWendang0100/css/popup.css
KafkaZhongwenWendang0100/font/__init__.py
KafkaZhongwenWendang0100/font/fontello.eot
KafkaZhongwenWendang0100/font/fontello.svg
KafkaZhongwenWendang0100/font/fontello.ttf
KafkaZhongwenWendang0100/font/fontello.woff
KafkaZhongwenWendang0100/img/__init__.py
KafkaZhongwenWendang0100/img/annotator-glyph-sprite.png
KafkaZhongwenWendang0100/img/annotator-icon-sprite.png
KafkaZhongwenWendang0100/img/apple-touch-icon.png
KafkaZhongwenWendang0100/img/cancelfullscreen.png
KafkaZhongwenWendang0100/img/close.png
KafkaZhongwenWendang0100/img/fullscreen.png
KafkaZhongwenWendang0100/img/loader.gif
KafkaZhongwenWendang0100/img/menu-icon.png
KafkaZhongwenWendang0100/img/save.png
KafkaZhongwenWendang0100/img/saved.png
KafkaZhongwenWendang0100/img/settings-s.png
KafkaZhongwenWendang0100/img/settings.png
KafkaZhongwenWendang0100/img/star.png
KafkaZhongwenWendang0100/js/__init__.py
KafkaZhongwenWendang0100/js/epub.js
KafkaZhongwenWendang0100/js/epub.min.js
KafkaZhongwenWendang0100/js/epub.min.map
KafkaZhongwenWendang0100/js/hooks.min.js
KafkaZhongwenWendang0100/js/hooks.min.map
KafkaZhongwenWendang0100/js/reader.js
KafkaZhongwenWendang0100/js/reader.js.map
KafkaZhongwenWendang0100/js/reader.min.js
KafkaZhongwenWendang0100/js/reader.min.map
KafkaZhongwenWendang0100/js/hooks/__init__.py
KafkaZhongwenWendang0100/js/hooks/extensions/__init__.py
KafkaZhongwenWendang0100/js/hooks/extensions/highlight.js
KafkaZhongwenWendang0100/js/libs/__init__.py
KafkaZhongwenWendang0100/js/libs/jquery.min.js
KafkaZhongwenWendang0100/js/libs/localforage.min.js
KafkaZhongwenWendang0100/js/libs/screenfull.js
kafka_zhongwen_wendang_0_10_0-2024.3.2.0.dist-info/METADATA
kafka_zhongwen_wendang_0_10_0-2024.3.2.0.dist-info/WHEEL
kafka_zhongwen_wendang_0_10_0-2024.3.2.0.dist-info/entry_points.txt
kafka_zhongwen_wendang_0_10_0-2024.3.2.0.dist-info/top_level.txt
kafka_zhongwen_wendang_0_10_0-2024.3.2.0.dist-info/RECORD
